{
  "key": "plugin_content_manager_configuration_components::components.afdelingen",
  "value": {
    "settings": {
      "bulkable": true,
      "filterable": true,
      "searchable": true,
      "pageSize": 10,
      "mainField": "afdelingId",
      "defaultSortBy": "afdelingId",
      "defaultSortOrder": "ASC"
    },
    "metadatas": {
      "id": {
        "edit": {},
        "list": {
          "label": "id",
          "searchable": false,
          "sortable": false
        }
      },
      "afdelingId": {
        "edit": {
          "label": "Identifier Afdeling",
          "description": "De unieke identifier van de afdeling.",
          "placeholder": "",
          "visible": true,
          "editable": true
        },
        "list": {
          "label": "afdelingId",
          "searchable": true,
          "sortable": true
        }
      },
      "afdelingNaam": {
        "edit": {
          "label": "afdelingNaam",
          "description": "",
          "placeholder": "",
          "visible": true,
          "editable": true
        },
        "list": {
          "label": "afdelingNaam",
          "searchable": true,
          "sortable": true
        }
      }
    },
    "layouts": {
      "list": ["id", "afdelingId", "afdelingNaam"],
      "edit": [
        [
          {
            "name": "afdelingId",
            "size": 6
          },
          {
            "name": "afdelingNaam",
            "size": 6
          }
        ]
      ]
    },
    "uid": "components.afdelingen",
    "isComponent": true
  },
  "type": "object",
  "environment": null,
  "tag": null
}
