{
  "key": "plugin_content_manager_configuration_components::components.identification-method",
  "value": {
    "uid": "components.identification-method",
    "settings": {
      "bulkable": true,
      "filterable": true,
      "searchable": true,
      "pageSize": 10,
      "mainField": "method",
      "defaultSortBy": "id",
      "defaultSortOrder": "ASC"
    },
    "metadatas": {
      "id": {
        "edit": {},
        "list": {
          "label": "id",
          "searchable": false,
          "sortable": false
        }
      },
      "method": {
        "edit": {
          "label": "Methode",
          "description": "",
          "placeholder": "",
          "visible": true,
          "editable": true
        },
        "list": {
          "label": "method",
          "searchable": true,
          "sortable": true
        }
      }
    },
    "layouts": {
      "list": ["id", "method"],
      "edit": [
        [
          {
            "name": "method",
            "size": 6
          }
        ]
      ]
    },
    "isComponent": true
  },
  "type": "object",
  "environment": null,
  "tag": null
}
